hashedpass/__init__.py
hashedpass/__main__.py
hashedpass/hashedpass.py
hashedpass/main.py
hashedpass-1.0.2.data/scripts/hashedpass
hashedpass-1.0.2.dist-info/LICENSE
hashedpass-1.0.2.dist-info/METADATA
hashedpass-1.0.2.dist-info/WHEEL
hashedpass-1.0.2.dist-info/top_level.txt
hashedpass-1.0.2.dist-info/RECORD
