Metadata-Version: 2.1
Name: hashedpass
Version: 1.0.2
Summary: Hashed-based password manager program/library.
Author-email: Emil Arner <arner@usa.com>
License: MIT License        
Project-URL: Homepage, https://github.com/emilarner/hashedpass
Classifier: Programming Language :: Python :: 3
Classifier: License :: OSI Approved :: MIT License
Classifier: Operating System :: Unix
Requires-Python: >=3.7
License-File: LICENSE
Requires-Dist: passlib
Requires-Dist: blessed
Requires-Dist: argon2-cffi
